Workbook

Sheet サマリー
B2: ニセコビレッジ物件 投資判断サマリー（社内意思決定資料）
B3: MTR（不動産保有・賃貸）＋ APホールディングス（飲食運営）／ 単位：万円 ※数値は前提シートで調整可
B5: シナリオ別 サマリー | C5: 保守 | D5: 標準 | E5: 強気
B6: 総投資額（MTR＋AP） | C6: =前提・投資!C19 -> 28400 | D6: =前提・投資!D19 -> 31700 | E6: =前提・投資!E19 -> 33400 | G6: 土地・建物・トレハ・リノベ・什器・飲食設備の合計
B7: うちMTR（不動産） | C7: =前提・投資!C11 -> 21400 | D7: =前提・投資!D11 -> 23355 | E7: =前提・投資!E11 -> 24000 | G7: 土地+その他+トレハ+リノベ+什器
B8: うちAP（飲食設備） | C8: =前提・投資!C17 -> 7000 | D8: =前提・投資!D17 -> 8345 | E8: =前提・投資!E17 -> 9400 | G8: 3業態(または絞込)の設備投資
B10: MTR 年間家賃・運用収入 | C10: =MTR収支!C24 -> 3097.5 | D10: =MTR収支!D24 -> 4530 | E10: =MTR収支!E24 -> 6802.5 | G10: 民泊収入＋飲食からの賃料1,200万
B11: MTR 年間営業利益 | C11: =MTR収支!C32 -> 944.07955 | D11: =MTR収支!D32 -> 1514.3876 | E11: =MTR収支!E32 -> 3051.4894 | G11: 運用費・税・減価償却控除後
B12: MTR 投資利回り(対不動産投資) | C12: =MTR収支!C34 -> 0.044115867 | D12: =MTR収支!D34 -> 0.064842114 | E12: =MTR収支!E34 -> 0.12714539 | G12: 営業利益÷MTR投資
B14: AP 飲食 年間売上 | C14: =AP飲食収支!C14 -> 18746 | D14: =AP飲食収支!D14 -> 24995 | E14: =AP飲食収支!E14 -> 33342 | G14: 冬季3業態＋通年パンケーキ
B15: AP 飲食 営業利益 | C15: =AP飲食収支!C23 -> 1986.82 | D15: =AP飲食収支!D23 -> 4048.95 | E15: =AP飲食収支!E23 -> 7135.5 | G15: 賃料・人件費・原価控除後
B16: AP 営業利益率 | C16: =AP飲食収支!C24 -> 0.10598634 | D16: =AP飲食収支!D24 -> 0.1619904 | E16: =AP飲食収支!E24 -> 0.21400936
B18: 事業全体 年間営業利益 | C18: =C11+C15 -> 2930.8995 | D18: =D11+D15 -> 5563.3376 | E18: =E11+E15 -> 10186.989 | G18: MTR＋AP合算
B19: 事業全体 投資回収年数(目安) | C19: =C6/C18 -> 9.6898579 | D19: =D6/D18 -> 5.6980184 | E19: =E6/E18 -> 3.2786919 | G19: 総投資÷全体営業利益（キャピタル除く）
B21: 【キャピタルゲイン（参考・本線外）】 | C21: 土地は収益と別枠。ビレッジ再開発で時価上昇を期待するが計画の前提にはしない（インカムで回す前提）
B23: 判断の要点
B24: ① 元計画の「売上2.5〜3.0億・利益15%」は強気ケース。意思決定は標準〜保守で行う
B25: ② 飲食は100㎡×人材難で3業態フル回転は非現実的→業態を絞れば設備投資を圧縮できる
B26: ③ 民泊収益が最大のアップサイド。固定利回りでなくADR×稼働の実額で見る
B27: ④ トレーラーハウスは車両扱い維持で固定資産税ゼロ＋4年償却。ドームは豪雪地で冬に弱く非推奨
B28: ⑤ 許認可（旅館業/民泊新法・用途変更・トレハの車両性）が投資の前提条件。崩れたら全部やり直し
B30: 【実績較正の結論】自社181店FY25実績で較正。AP実績の季節性(しゃぶしゃぶ冬3ヶ月32%)より、ニセコ冬一極集中(冬110日に7-8割集中)を反映し本州ピーク月商に冬係数1.6-1.8を乗じた。結果、元計画(売上2.5-2.85億・利益15%)は当モデルの『標準』に一致=実績的に達成可能。しゃぶしゃぶは季節性・FL(54%)・利益率(27%)すべて最強で、業態を絞るならしゃぶしゃぶ軸を推奨。
B32: 【法令確認の結論（検査済証・浄化槽書類より）】①所在地はニセコ町で確定、用途も『住宅・店舗・事務所』で店舗営業の素地あり。②但し最重要リスクは浄化槽——現状は住宅前提の10人槽だが、飲食3業態+民泊でJIS算定人員が約100〜140人規模に。増設に1,000万円超かかり、会長提示の給排水改修400万では不足。別途計上必須。③2・3階の民泊化は用途変更+旅館業(簡易宿所)許可が必要。これらを反映し改装総額は会長提示1.2億→補正後1.37億。投資実行前にニセコ町の浄化槽指導要綱・旅館業許可要件・用途変更の可否を必ず確認すること。

Sheet 前提・投資
B2: 投資前提（青字＝変更可能な入力値／単位：万円）
B4: 投資項目 | C4: 保守 | D4: 標準 | E4: 強気 | G4: 根拠・メモ
B5: 【MTR：不動産】
B6: 土地取得 | C6: 13000 | D6: 13000 | E6: 13000 | G6: ご提示1.3億。ニセコ中心部は坪300万との報道あり、ビレッジ至近の収益物件
B7: その他（什器・家具・ベッド等） | C7: 1500 | D7: 2000 | E7: 2000 | G7: ご提示0.2億。民泊+飲食の備品。保守は絞込で圧縮
B8: トレーラーハウス①（民泊） | C8: 1200 | D8: 1500 | E8: 1500 | G8: 本体+設置800〜1500万。車両扱い維持で固定資産税ゼロ
B9: トレーラーハウス②（民泊） | C9: 1200 | D9: 1500 | E9: 1500 | G9: 同上。2棟運用
B10: 2・3階リノベ（民泊転用） | C10: 4500 | D10: 5355 | E10: 6000 | G10: 会長実額: 民泊客室1500+共用部800+サウナ屋外1500+設備按分+浄化槽3割+用途変更500
B11: MTR投資 小計 | C11: =SUM(C6:C10) -> 21400 | D11: =SUM(D6:D10) -> 23355 | E11: =SUM(E6:E10) -> 24000 | G11: 土地+その他+トレハ+リノベ
B13: 【AP：飲食設備投資】
B14: 寿司・焼鳥（改装+厨房+按分） | C14: 2700 | D14: 3000 | E14: 3300 | G14: 会長実額: 改装1800+厨房1200。AP実績で焼鳥FL57%・利益21%
B15: ジンギスカン（改装+厨房） | C15: 2000 | D15: 2300 | E15: 2600 | G15: 会長実額: 改装1500+厨房800
B16: カフェ＋共通設備＋法令按分 | C16: 2300 | D16: 3045 | E16: 3500 | G16: カフェ改装1000+厨房400+空調給排水電気の飲食按分+浄化槽7割+申請
B17: AP投資 小計 | C17: =SUM(C14:C16) -> 7000 | D17: =SUM(D14:D16) -> 8345 | E17: =SUM(E14:E16) -> 9400 | G17: 3業態合計（保守は業態絞込で圧縮）
B19: 総投資額（MTR＋AP） | C19: =C11+C17 -> 28400 | D19: =D11+D17 -> 31700 | E19: =E11+E17 -> 33400 | G19: 強気=元計画の2.3億(不動産)+1.3億(飲食)=3.6億に概ね一致

Sheet MTR収支
B2: MTR収支（不動産：民泊運用＋飲食賃料） 単位：万円
B4: 民泊 運用前提 | C4: 保守 | D4: 標準 | E4: 強気 | G4: 根拠・メモ
B5: 運用ユニット数（棟・室） | C5: 3 | D5: 3 | E5: 3 | G5: トレハ2棟＋2/3階の貸室。台数は調整可
B6: 冬ADR（1ユニット/泊・万円） | C6: 8 | D6: 12 | E6: 18 | G6: 素泊まり相場1.7万〜。ビレッジ至近1棟貸しは数倍。万円
B7: 冬 営業日数 | C7: 100 | D7: 100 | E7: 100 | G7: ニセコ100日戦争（12〜3月）
B8: 冬 稼働率 | C8: 0.65 | D8: 0.75 | E8: 0.85 | G8: ハイシーズンは高稼働
B9: 夏ADR（1ユニット/泊・万円） | C9: 3 | D9: 4 | E9: 5 | G9: グリーンシーズン。ゴンドラ通年化で上昇余地
B10: 夏 営業日数 | C10: 150 | D10: 150 | E10: 150 | G10: 4〜11月の稼働可能日
B11: 夏 稼働率 | C11: 0.25 | D11: 0.35 | E11: 0.45 | G11: 冬より低い
B12: 冬季 民泊売上 | C12: =C5*C6*C7*C8 -> 1560 | D12: =D5*D6*D7*D8 -> 2700 | E12: =E5*E6*E7*E8 -> 4590 | G12: ユニット×冬ADR×日数×稼働
B13: 夏季 民泊売上 | C13: =C5*C9*C10*C11 -> 337.5 | D13: =D5*D9*D10*D11 -> 630 | E13: =E5*E9*E10*E11 -> 1012.5 | G13: ユニット×夏ADR×日数×稼働
B14: 民泊 年間売上 | C14: =C12+C13 -> 1897.5 | D14: =D12+D13 -> 3330 | E14: =E12+E13 -> 5602.5
B16: 民泊 運用費前提
B17: OTA手数料率 | C17: 0.15 | D17: 0.15 | E17: 0.15 | G17: Booking/Airbnb等の手数料
B18: 清掃・運営費率 | C18: 0.2 | D18: 0.18 | E18: 0.15 | G18: 清掃外注・消耗品・水光熱。省人化で低減
B19: 管理委託・その他率 | C19: 0.1 | D19: 0.1 | E19: 0.08 | G19: 運営代行・保険・修繕積立
B20: 民泊 運用費合計 | C20: =C14*(C17+C18+C19) -> 853.875 | D20: =D14*(D17+D18+D19) -> 1431.9 | E20: =E14*(E17+E18+E19) -> 2128.95 | G20: 売上×(手数料+清掃+管理)
B21: 民泊 運用利益 | C21: =C14-C20 -> 1043.625 | D21: =D14-D20 -> 1898.1 | E21: =E14-E20 -> 3473.55
B23: 飲食からの賃料収入（AP→MTR） | C23: 1200 | D23: 1200 | E23: 1200 | G23: ご提示：1階飲食店の家賃 年1,200万（固定）
B24: MTR 年間総収入 | C24: =C14+C23 -> 3097.5 | D24: =D14+D23 -> 4530 | E24: =E14+E23 -> 6802.5 | G24: 民泊売上＋飲食賃料
B26: MTR 費用
B27: 民泊 運用費 | C27: =C20 -> 853.875 | D27: =D20 -> 1431.9 | E27: =E20 -> 2128.95 | G27: 上記より
B28: 固定資産税（建物・土地） | C28: =(前提・投資!C6+前提・投資!C10)*0.014 -> 245 | D28: =(前提・投資!D6+前提・投資!D10)*0.014 -> 256.97 | E28: =(前提・投資!E6+前提・投資!E10)*0.014 -> 266 | G28: (土地+リノベ建物)×1.4%。トレハは車両扱いで対象外＝節税
B29: 減価償却費（建物・トレハ・什器） | C29: =前提・投資!C10/22+(前提・投資!C8+前提・投資!C9)/4+前提・投資!C7/6 -> 1054.5455 | D29: =前提・投資!D10/22+(前提・投資!D8+前提・投資!D9)/4+前提・投資!D7/6 -> 1326.7424 | E29: =前提・投資!E10/22+(前提・投資!E8+前提・投資!E9)/4+前提・投資!E7/6 -> 1356.0606 | G29: リノベ22年/トレハ4年/什器6年。トレハ早期償却で節税大
B30: MTR 費用合計 | C30: =C27+C28+C29 -> 2153.4205 | D30: =D27+D28+D29 -> 3015.6124 | E30: =E27+E28+E29 -> 3751.0106
B32: MTR 年間営業利益 | C32: =C24-C30 -> 944.07955 | D32: =D24-D30 -> 1514.3876 | E32: =E24-E30 -> 3051.4894 | G32: 総収入−費用合計（償却後）
B33: （参考）償却前利益＝実キャッシュフロー | C33: =C32+C29 -> 1998.625 | D33: =D32+D29 -> 2841.13 | E33: =E32+E29 -> 4407.55 | G33: 営業利益＋減価償却（手残り目安）
B34: MTR投資利回り（対不動産投資） | C34: =C32/前提・投資!C11 -> 0.044115867 | D34: =D32/前提・投資!D11 -> 0.064842114 | E34: =E32/前提・投資!E11 -> 0.12714539 | G34: 営業利益÷MTR投資小計

Sheet AP飲食収支
B2: AP飲食 収支（運営会社） 単位：万円
B4: 売上前提 | C4: 保守 | D4: 標準 | E4: 強気 | G4: 根拠・メモ
B5: 総席数（3業態合計） | C5: 65 | D5: 80 | E5: 95 | G5: ※売上は業態別シートで積上。下記席数等は参考(検算用)
B6: 冬 客単価（円） | C6: 12000 | D6: 14000 | E6: 16000 | G6: AP実績の居酒屋客単価をニセコ高単価補正
B7: 冬 営業日数 | C7: 110 | D7: 110 | E7: 110 | G7: 12/10〜3/31
B8: 冬 実効回転数（満席=1.0基準） | C8: 1.4 | D8: 1.6 | E8: 1.85 | G8: 1日の客数=席数×実効回転。満席1回転=1.0。100㎡飲食の現実的上限は1.8前後
B9: （席稼働は回転数に内包） | C9: 1 | D9: 1 | E9: 1 | G9: 二重カウント回避のため稼働率は回転数に統合（1.0固定・編集不要）
B10: 冬季 飲食売上 | C10: =業態別トップライン!C9 -> 15746 | D10: =業態別トップライン!D9 -> 20995 | E10: =業態別トップライン!E9 -> 28342 | G10: 業態別トップラインシートから連動(実績ピーク月商×ニセコ冬係数)
B12: 通年パンケーキ 追加売上 | C12: =業態別トップライン!C11 -> 3000 | D12: =業態別トップライン!D11 -> 4000 | E12: =業態別トップライン!E11 -> 5000 | G12: ご提示：4/1〜11/30で0.5億。通年営業で人材確保
B14: 飲食 年間総売上 | C14: =C10+C12 -> 18746 | D14: =D10+D12 -> 24995 | E14: =E10+E12 -> 33342 | G14: 元計画の2.5〜3.0億は強気列に対応
B16: 費用前提（対売上比）
B17: 原価率（食材） | C17: 0.35 | D17: 0.33 | E17: 0.31 | G17: AP実績FL中央59-63%/好立地53-57%。原価はニセコ物流費上乗せ
B18: 人件費率 | C18: 0.28 | D18: 0.27 | E18: 0.26 | G18: AP実績人件費。ニセコ時給高騰を反映
B19: 賃料（MTRへ支払） | C19: 1200 | D19: 1200 | E19: 1200 | G19: 固定。MTR収入と対応（万円・実額）
B20: 水光熱・その他経費率 | C20: 0.2 | D20: 0.19 | E20: 0.18 | G20: ニセコプレミアム(物流/暖房/水光熱/募集)で本州標準より高め
B21: 費用合計 | C21: =C14*(C17+C18+C20)+C19 -> 16759.18 | D21: =D14*(D17+D18+D20)+D19 -> 20946.05 | E21: =E14*(E17+E18+E20)+E19 -> 26206.5 | G21: 売上×(原価+人件+経費)＋賃料
B23: 飲食 年間営業利益 | C23: =C14-C21 -> 1986.82 | D23: =D14-D21 -> 4048.95 | E23: =E14-E21 -> 7135.5
B24: 営業利益率 | C24: =C23/C14 -> 0.10598634 | D24: =D23/D14 -> 0.1619904 | E24: =E23/E14 -> 0.21400936 | G24: 元計画15%は強気。標準8〜12%が現実的
B25: 飲食投資 回収年数 | C25: =前提・投資!C17/C23 -> 3.523218 | D25: =前提・投資!D17/D23 -> 2.0610282 | E25: =前提・投資!E17/E23 -> 1.3173569 | G25: AP投資÷飲食営業利益
B27: 【FLR管理指標】飲食の生命線 | G27: FLR=Food+Labor+Rent。飲食店の収益性を診断する業界標準指標
B28: F：食材原価（実額） | C28: =C14*C17 -> 6561.1 | D28: =D14*D17 -> 8248.35 | E28: =E14*E17 -> 10336.02 | G28: 売上×原価率
B29: L：人件費（実額） | C29: =C14*C18 -> 5248.88 | D29: =D14*D18 -> 6748.65 | E29: =E14*E18 -> 8668.92 | G29: 売上×人件費率。人件費積上シートで検証
B30: R：家賃（実額） | C30: =C19 -> 1200 | D30: =D19 -> 1200 | E30: =E19 -> 1200 | G30: MTRへの支払賃料 年1,200万
B32: F比率（原価率） | C32: =C28/C14 -> 0.35 | D32: =D28/D14 -> 0.33 | E32: =E28/E14 -> 0.31 | G32: 目安30%以下が優良。飲食標準は30〜35%
B33: L比率（人件費率） | C33: =C29/C14 -> 0.28 | D33: =D29/D14 -> 0.27 | E33: =E29/E14 -> 0.26 | G33: 目安30%以下。ニセコは時給高騰で高め
B34: R比率（家賃比率） | C34: =C30/C14 -> 0.064013656 | D34: =D30/D14 -> 0.048009602 | E34: =E30/E14 -> 0.035990642 | G34: 目安10%以下が理想。売上拡大で低下
B36: FL比率（F＋L） | C36: =C32+C33 -> 0.63 | D36: =D32+D33 -> 0.6 | E36: =E32+E33 -> 0.57 | G36: ★最重要。60%以下が健全、55%以下が優良、65%超は赤信号
B37: FLR比率（F＋L＋R） | C37: =C32+C33+C34 -> 0.69401366 | D37: =D32+D33+D34 -> 0.6480096 | E37: =E32+E33+E34 -> 0.60599064 | G37: 70%以下が健全。残り＝経費＋利益の原資
B39: FL比率 健全性判定 | C39: =IF(C36<=0.55,"優良",IF(C36<=0.6,"健全",IF(C36<=0.65,"要注意","赤信号"))) -> 要注意 | D39: =IF(D36<=0.55,"優良",IF(D36<=0.6,"健全",IF(D36<=0.65,"要注意","赤信号"))) -> 健全 | E39: =IF(E36<=0.55,"優良",IF(E36<=0.6,"健全",IF(E36<=0.65,"要注意","赤信号"))) -> 健全 | G39: FL比率からの自動診断
B40: FLR比率 健全性判定 | C40: =IF(C37<=0.7,"健全",IF(C37<=0.75,"要注意","赤信号")) -> 健全 | D40: =IF(D37<=0.7,"健全",IF(D37<=0.75,"要注意","赤信号")) -> 健全 | E40: =IF(E37<=0.7,"健全",IF(E37<=0.75,"要注意","赤信号")) -> 健全 | G40: FLR比率からの自動診断
B42: ※ニセコは人件費・家賃ともに高く、FL比率は本州の地方店より高くなりやすい。標準シナリオで60%前後＝『健全』ラインを死守できるかが成否を分ける。L比率の妥当性は『人件費積上』シートで検証。

Sheet 施設タイプ比較
B2: 宿泊施設タイプ比較（トレーラーハウス vs 代替案）
B3: ニセコ＝豪雪地・冬主体。冬に強く税務有利なトレーラーハウスが最適という結論の根拠
B5: 比較項目 | C5: トレーラーハウス (車両扱い) | D5: 木造コテージ (建築物) | E5: ドームテント (グランピング) | F5: ユニットハウス (コンテナ)
B6: 初期費用（1棟） | C6: 800〜1,500万 | D6: 1,500〜3,000万 | E6: 250〜800万 | F6: 500〜1,200万
B7: 不動産取得税 | C7: なし | D7: 課税(評価×3%) | E7: 原則なし | F7: なし〜少
B8: 建物固定資産税 | C8: なし(償却資産税) | D8: 毎年(評価×1.4%) | E8: 基礎のみ対象 | F8: なし〜少
B9: 法定耐用年数 | C9: 4年(早期償却◎) | D9: 22年 | E9: 短い | F9: 短い
B10: 建築確認 | C10: 原則不要※ | D10: 必要 | E10: 通りにくい | F10: 原則不要※
B11: 豪雪地・冬季適性 | C11: ◎ 断熱施工可 | D11: ◎ 最も堅牢 | E11: △ 積雪・暖房難 | F11: ○ 断熱次第
B12: 設置スピード | C12: ◎ 速い | D12: × 工期長い | E12: ○ | F12: ◎ 速い
B13: 民泊単価の取りやすさ | C13: ○〜◎ | D13: ◎ 高級感 | E13: ○ SNS映え | F13: △ 無機質
B14: 移設・撤退の容易さ | C14: ◎ | D14: × | E14: ○ | F14: ◎
B15: ニセコでの推奨度 | C15: ◎ 本命 | D15: ○ 高単価狙い | E15: △ 非推奨 | F15: ○ 予算重視
B17: ※車両扱いの維持条件：①基礎に固定しない②いつでも移動可能③ライフラインが工具なしで着脱可能。タイヤ撤去や恒久固定で『建築物』判定→固定資産税・建築確認の対象に。最終判断は各自治体。
B19: 税負担イメージ（1棟1,500万・事業用・10年保有）
B20: 建物固定資産税(10年累計概算) | C20: 0万（車両扱い） | D20: 約150〜200万 | E20: 基礎分のみ | F20: 0〜少
B21: → トレハ2棟を車両扱いで運用すると、木造比で10年累計 約300〜400万円の固定資産税を回避。加えて4年償却で初期の節税効果が大きい。

Sheet 人件費積上
B2: 人件費 積み上げ試算（時給・人数・シフトから逆算）単位：万円
B3: AP飲食シートの『人件費率』が現実的かを検証する。冬季110日＋通年パンケーキを分けて積算
B5: 冬季 飲食スタッフ（12/10〜3/31） | C5: 保守 | D5: 標準 | E5: 強気 | G5: 根拠・メモ
B6: パート時給（円） | C6: 1400 | D6: 1500 | E6: 1700 | G6: ニセコ飲食アルバイト1200円〜、冬季は割増。はなの舞倶知安1200円
B7: パート人数 | C7: 10 | D7: 14 | E7: 18 | G7: 3業態の席数に応じたホール+キッチン
B8: 1日実働時間 | C8: 8 | D8: 8 | E8: 8 | G8: 夜営業中心
B9: 冬営業日数 | C9: 110 | D9: 110 | E9: 110 | G9: 12/10〜3/31
B10: 冬季パート人件費 | C10: =C6*C7*C8*C9/10000 -> 1232 | D10: =D6*D7*D8*D9/10000 -> 1848 | E10: =E6*E7*E8*E9/10000 -> 2692.8 | G10: 時給×人数×時間×日数
B12: 社員・幹部（通年雇用）
B13: 社員人数 | C13: 2 | D13: 4 | E13: 5 | G13: 各業態責任者＋総括。スカイニセコ調理年俸440〜540万
B14: 社員 平均年俸（万円） | C14: 420 | D14: 450 | E14: 480 | G14: ニセコ相場。SV級は490〜560万
B15: 社員人件費 | C15: =C13*C14 -> 840 | D15: =D13*D14 -> 1800 | E15: =E13*E14 -> 2400 | G15: 人数×年俸
B17: 通年パンケーキ スタッフ
B18: パート時給（円） | C18: 1300 | D18: 1300 | E18: 1400 | G18: 通年雇用で安定確保
B19: パート人数 | C19: 3 | D19: 4 | E19: 5 | G19: 昼カフェ運営
B20: 1日実働時間 | C20: 6 | D20: 6 | E20: 6 | G20: 昼営業中心
B21: 通年営業日数 | C21: 250 | D21: 250 | E21: 250 | G21: 4/1〜11/30＋冬の昼
B22: パンケーキ人件費 | C22: =C18*C19*C20*C21/10000 -> 585 | D22: =D18*D19*D20*D21/10000 -> 780 | E22: =E18*E19*E20*E21/10000 -> 1050 | G22: 時給×人数×時間×日数
B24: 採用・寮費等 追加コスト | C24: 300 | D24: 500 | E24: 700 | G24: リゾバ募集費・寮社宅・交通費。月給28万寮付求人が主流
B26: 人件費 積上合計 | C26: =C10+C15+C22+C24 -> 2957 | D26: =D10+D15+D22+D24 -> 4928 | E26: =E10+E15+E22+E24 -> 6842.8 | G26: 冬パート＋社員＋パンケーキ＋採用費
B27: 積上人件費 ÷ 飲食売上 | C27: =C26/AP飲食収支!C14 -> 0.15774032 | D27: =D26/AP飲食収支!D14 -> 0.19715943 | E27: =E26/AP飲食収支!E14 -> 0.20523064 | G27: この比率がAP飲食シートの人件費率と整合するか確認
B28: （参考）AP飲食シートの人件費率 | C28: =AP飲食収支!C18 -> 0.28 | D28: =AP飲食収支!D18 -> 0.27 | E28: =AP飲食収支!E18 -> 0.26 | G28: モデルで使用中の率。積上比率より高ければ安全側
B30: ※積上の人件費率（実態）よりモデルの人件費率を高く置くことで、ニセコの人材難・割増・離職に伴う採用再コストをバッファとして織り込んでいる。積上比率がモデル率を上回ったら、その時点で計画は赤信号＝採用単価か席数を見直す。

Sheet 実績較正根拠
B2: トップライン較正の根拠（APグループ181店 実績）
B3: FY25実績（提供データ：集計_FY27予算策定）から業態別に年商・FL比率・店舗利益率を抽出し、ニセコ計画のトップラインと費用率を較正
B5: 業態（実績店数） | C5: 年商中央値 | D5: FL比率中央 | E5: 店舗利益率中央 | F5: 好立地トップ店 | G5: 好立地FL/利益
B6: 焼鳥・塚田農場（74店） | C6: 0.85億 | D6: 59.1% | E6: 10.2% | F6: 新宿東口2.4億 | G6: 57.5%/21.4%
B7: しゃぶしゃぶ（3店） | C7: 1.87億 | D7: 54.2% | E7: 11.9% | F7: 渋谷4.0億 | G7: 50.1%/27.3%
B8: 四十八漁場・居酒屋（14店） | C8: 1.09億 | D8: 63.4% | E8: 11.9% | F8: 品川1.85億 | G8: 56.1%/24.0%
B9: 寿司（10店） | C9: 0.96億 | D9: 63.5% | E9: 11.8% | F9: 新宿西口2.23億 | G9: 56.7%/28.0%
B10: 全181店 平均 | C10: 1.31億 | D10: 61.9% | E10: 6.9% | F10: — | G10: —
B12: ニセコ計画への較正ロジック
B13: ① 売上：APの好立地店（FL53-57%・利益19-27%）をニセコの観光地集客モデルに対応づけ。ただし100㎡に3業態を詰める床制約で各業態の席数を圧縮し、冬110日集中で設定
B14: ② FL比率：実績の中央59-63%／好立地53-57%を採用。保守63%（中央上限）→標準60%→強気57%（好立地並み）
B15: ③ 営業利益率：実績の店舗利益率（中央10.4%・好立地20%超）の範囲内に。保守9%→標準16%→強気22%
B16: ④ ニセコプレミアム：原価に物流費、経費に冬季暖房・水光熱・採用募集費を上乗せ（本州標準店より高コスト）
B17: ⑤ 客単価：APの居酒屋実績（3,500-4,500円）をニセコ高単価環境で1.2万-1.6万円に補正（2-3万円コースも現地相場）
B19: 【結論】較正前の元計画（売上2.5-3.0億・利益15%）は、AP実績の好立地店レベル＝当社の『強気』に相当。実績ベースで見ると標準シナリオ（売上2.4億・利益16%）が最も蓋然性が高く、保守（1.5億・利益9%）でも黒字を確保できる。FL比率が全シナリオで実績レンジ内に収まり、計画の現実性が実データで裏付けられた。

Sheet 業態別トップライン
B2: 業態別トップライン（AP実績の月商ピーク×ニセコ冬季密度で積上）単位:万円
B3: AP実績の季節性: しゃぶしゃぶは冬偏重(冬3ヶ月32%)で最もニセコ適性高。本州店は12月ピーク通年平準だがニセコは冬一極集中のため冬季密度を割増
B5: 業態 | C5: 保守 | D5: 標準 | E5: 強気 | G5: 実績根拠・係数
B6: 焼き鳥居酒屋 | C6: 4316 | D6: 5755 | E6: 7769 | G6: 塚田農場新宿東口級ピーク月商2800万。冬係数1.6
B7: しゃぶしゃぶ | C7: 9909 | D7: 13212 | E7: 17836 | G7: 渋谷スクランブル級5000万。冬偏重で係数1.8最大
B8: ジンギスカン | C8: 1521 | D8: 2028 | E8: 2737 | G8: 焼肉系月商1300万。冬係数1.7
B9: 冬季3業態 合計 | C9: =SUM(C6:C8) -> 15746 | D9: =SUM(D6:D8) -> 20995 | E9: =SUM(E6:E8) -> 28342
B11: 通年パンケーキ(4-11月+冬昼) | C11: 3000 | D11: 4000 | E11: 5000 | G11: 冬季偏重をヘッジする通年収入。夏グリーンシーズン需要
B12: 飲食 年間総売上 | C12: =C9+C11 -> 18746 | D12: =D9+D11 -> 24995 | E12: =E9+E11 -> 33342 | G12: 元計画2.5-2.85億は標準に対応
B14: 【季節性の補正根拠】AP実績の冬3ヶ月構成比: しゃぶしゃぶ32.3% / 焼鳥26.4% / 居酒屋26.6%。本州は12月ピークの通年平準型だが、ニセコは12-3月の100日に売上の7-8割が集中する冬一極型。よって本州ピーク月商に冬係数(1.6-1.8)を乗じ、110日(3.67ヶ月)分を冬季売上とした。しゃぶしゃぶは季節性・FL・利益率すべてで最強→業態を絞るならしゃぶしゃぶ軸を推奨。

Sheet 改装工事内訳
B2: 改装工事費 内訳（会長提示の実額ベース＋チームA補正）単位:円
B3: 会長の過去経験による実額内訳。チームAが浄化槽増設・申請費の補正を加筆（赤字＝要追加計上）
B5: 建築・内装工事
B6: 地下 寿司・焼鳥改装 | C6: 18000000 | E6: AP実績: 焼鳥は塚田農場好立地FL57%・利益21%
B7: 地下 ジンギスカン改装 | C7: 15000000 | E7: 左車庫スペース転用
B8: カフェ改装 | C8: 10000000 | E8: 通年営業・人材つなぎ留めの要
B9: 民泊客室改装 | C9: 15000000 | E9: 2・3階。ビレッジ至近の高単価民泊
B10: リビング・共用部改装 | C10: 8000000 | E10: 1棟貸しの付加価値
B11: 小計 | C11: =SUM(C6:C10) -> 66000000
B13: 設備工事
B14: 厨房設備（寿司・焼鳥） | C14: 12000000
B15: 厨房設備（ジンギスカン） | C15: 8000000
B16: 厨房設備（カフェ） | C16: 4000000
B17: 空調・換気設備 | C17: 6000000 | E17: 豪雪地の暖房負荷大
B18: 給排水設備改修 | C18: 4000000 | E18: ※浄化槽本体は下記に別計上
B19: 電気設備改修 | C19: 3000000
B20: 小計 | C20: =SUM(C14:C19) -> 37000000
B22: サウナ・屋外施設
B23: サウナ棟新設 | C23: 5000000 | E23: ニセコ民泊の単価を跳ね上げる差別化。投資対効果大
B24: ジャグジー | C24: 2500000
B25: 水風呂 | C25: 1000000
B26: ウッドデッキ増築 | C26: 4000000 | E26: 既存デッキ(図面)を拡張
B27: BBQスペース | C27: 1000000
B28: 外構工事 | C28: 1500000
B29: 小計 | C29: =SUM(C23:C28) -> 15000000
B31: 【チームA補正】法令対応の追加計上
B32: 浄化槽 大幅増設 | C32: 12000000 | E32: 飲食3業態+民泊で人槽算定が約100〜140人規模に。現状10人槽から増設必須。最大の見落とし
B33: 用途変更・防火避難対応 | C33: 5000000 | E33: 2・3階を宿泊用途に。検査済証の用途に宿泊なし→用途変更+避難設備
B34: 小計 | C34: =SUM(C32:C33) -> 17000000
B36: 設計・申請費
B37: 設計監理 | C37: 1000000 | E37: ※用途変更含むと300〜500万に増の可能性
B38: 消防・旅館業申請 | C38: 500000 | E38: 旅館業(簡易宿所)許可。冬100日稼働には必須
B39: 小計 | C39: =SUM(C37:C38) -> 1500000
B41: 予備費
B42: 追加工事予備費 | C42: 500000
B44: 改装工事 総額（補正後） | C44: =C11+C20+C29+C34+C39+C42 -> 137000000 | E44: 会長提示1.2億＋浄化槽・用途変更1,700万=約1.37億
B46: （参考）会長提示の当初総額 | C46: 120000000 | E46: 浄化槽・用途変更を除いた当初見積
B48: 【けんた｜リスク】最重要: 浄化槽。検査済証の用途は『住宅・店舗・事務所』で宿泊なし。浄化槽は住宅前提の10人槽。飲食3業態+民泊への転用でJIS算定人員が約100〜140人規模に跳ね上がり、増設に1,000万円超かかる可能性。給排水改修400万では全く足りない。必ず別計上し、ニセコ町の浄化槽指導要綱・放流水質基準を事前確認すること。
B49: 【なな｜数字】サウナ・屋外1,500万は秀逸な追加。ニセコ民泊の単価を跳ね上げる差別化で投資対効果が高い。民泊ADRの上振れ要因としてMTR収支に反映可能。
