Workbook

Sheet 前提
A1: 南千歳ヴィラ 民泊収支モデル
A2: 北海道千歳市柏陽5丁目1-3 ／ 10ベッド・サウナ・BBQ ／ 一棟貸し
A3: 住居専用地域：金正午〜日正午のみ営業（週2泊）＝年間営業上限 約104泊
A5: ■ 共通前提
A6: 年間営業上限 | B6: 104 | C6: 泊 | D6: 住居専用地域 週末規制（金正午〜日正午）
A7: 定員 | B7: 10 | C7: 名 | D7: 10ベッド
A8: 清掃費（1回あたり） | B8: 18000 | C8: 円/回 | D8: ハウスクリーニング外注。稼働1泊ごとに発生
A9: ライト委託費（月額固定） | B9: 15000 | C9: 円/月 | D9: Bスタート：名義＋管理責任のみ。実務は自社
A10: 消耗品・アメニティ（売上比） | B10: 0.05 | C10: % | D10: リネン・備品・ゲスト用消耗品
A11: OTA手数料（売上比） | B11: 0.15 | C11: % | D11: Airbnb等プラットフォーム手数料
A12: 水道光熱費（月額固定） | B12: 40000 | C12: 円/月 | D12: 冬季暖房・サウナで増。年間ならし
A13: A登録後の委託費 | B13: 0 | C13: 円/月 | D13: 管理業者登録完了後は委託費ゼロ（自社管理）
A15: ※ 黄色セル＝変更可能な前提値（ブルー字）。シナリオはここを動かす。

Sheet 季節別単価
A1: 季節別ダイナミックプライシング
A2: 北海道の一棟貸しは冬（スキー・年末年始・インバウンド）がピーク。夏冬で単価2倍超の差をつける。
A4: シーズン | B4: 期間の目安 | C4: 配分泊数 | D4: 稼働率 | E4: 単価/泊 | F4: 稼働泊数 | G4: 売上 | H4: 備考
A5: 厳冬期ピーク | B5: 12月下旬〜2月（年末年始・スキー） | C5: 28 | D5: 0.85 | E5: 150000 | F5: =C5*D5 -> 23.8 | G5: =F5*E5 -> 3570000 | H5: インバウンド・スキー客。最高単価帯
A6: 冬準ピーク | B6: 3月・12月上旬（スノー残） | C6: 16 | D6: 0.75 | E6: 110000 | F6: =C6*D6 -> 12 | G6: =F6*E6 -> 1320000 | H6: スキー継続。年末年始外し
A7: 夏ハイ | B7: 7〜8月（盆・BBQ・ゴルフ） | C7: 24 | D7: 0.75 | E7: 95000 | F7: =C7*D7 -> 18 | G7: =F7*E7 -> 1710000 | H7: BBQ・ゴルフ・避暑。グループ需要
A8: 春秋ミドル | B8: 4〜6月・9〜10月（連休・紅葉） | C8: 24 | D8: 0.65 | E8: 75000 | F8: =C8*D8 -> 15.6 | G8: =F8*E8 -> 1170000 | H8: GW・シルバーウィーク・紅葉ゴルフ
A9: 閑散 | B9: 11月・夏冬端境 | C9: 12 | D9: 0.55 | E9: 60000 | F9: =C9*D9 -> 6.6 | G9: =F9*E9 -> 396000 | H9: 端境期。連泊割引で底上げ
A10: 合計 / 加重平均 | C10: =SUM(C5:C9) -> 104 | F10: =SUM(F5:F9) -> 76 | G10: =SUM(G5:G9) -> 8166000 | H10: 配分泊数は上限104泊以内で配分
A12: 配分泊数チェック（≤104） | C12: =IF(C10<=前提!B6,"OK ✓","超過！") -> OK ✓
A13: 加重平均単価/泊 | C13: =G10/F10 -> 107447.37

Sheet 年間収支
A1: 年間収支シミュレーション（標準シナリオ）
A2: 季節別ダイナミックプライシング反映。営業104泊・季節別配分ベース。
A4: 【売上】
A5: 宿泊売上（年間） | B5: =季節別単価!G10 -> 8166000 | D5: 季節別シートの合計売上
A6: 稼働泊数（年間） | B6: =季節別単価!F10 -> 76 | D6: 実際に泊まる延べ泊数
A7: 【変動費】
A8: 清掃費 | B8: =B6*前提!B8 -> 1368000 | D8: 稼働1泊ごと × 清掃単価
A9: OTA手数料 | B9: =B5*前提!B11 -> 1224900 | D9: 売上 × 手数料率
A10: 消耗品・アメニティ | B10: =B5*前提!B10 -> 408300 | D10: 売上 × 消耗品率
A11: 【固定費】
A12: ライト委託費（年） | B12: =前提!B9*12 -> 180000 | D12: Bスタート：月額固定×12。A登録後は0に
A13: 水道光熱費（年） | B13: =前提!B12*12 -> 480000 | D13: 冬季サウナ・暖房で増
A14: 【利益】
A15: 営業利益（年） | B15: =B5-B8-B9-B10-B12-B13 -> 4504800 | D15: 売上−変動費−固定費
A16: 営業利益率 | B16: =B15/B5 -> 0.5516532
A17: A登録後 営業利益（委託費0） | B17: =B15+B12 -> 4684800 | D17: 管理業者登録完了後：委託費が消える
A19: ※ 初期投資（消防設備・内装・サウナ整備等）は別途見積り。10ベッド規模は消防法上の設備要求に注意。

Sheet シナリオ比較
A1: 3シナリオ比較
A2: 季節別配分は標準シートと同一。稼働率と単価感応度を比較。
A4: 指標 | B4: 保守 | C4: 標準 | D4: 強気 | E4: 前提
A5: 稼働率係数 | B5: 0.85 | C5: 1 | D5: 1.15 | E5: 標準=季節別シートの稼働率
A6: 単価係数 | B6: 0.85 | C6: 1 | D6: 1.15 | E6: 標準=季節別シートの単価
A8: 年商 | B8: =季節別単価!G10*B5*B6 -> 5899935 | C8: =季節別単価!G10*C5*C6 -> 8166000 | D8: =季節別単価!G10*D5*D6 -> 10799535
A9: 変動費＋固定費 | B9: =(季節別単価!F10*B5)*前提!B8+B8*(前提!B11+前提!B10)+前提!B9*12+前提!B12*12 -> 3002787 | C9: =(季節別単価!F10*C5)*前提!B8+C8*(前提!B11+前提!B10)+前提!B9*12+前提!B12*12 -> 3661200 | D9: =(季節別単価!F10*D5)*前提!B8+D8*(前提!B11+前提!B10)+前提!B9*12+前提!B12*12 -> 4393107
A10: 営業利益 | B10: =B8-B9 -> 2897148 | C10: =C8-C9 -> 4504800 | D10: =D8-D9 -> 6406428
A11: 営業利益率 | B11: =B10/B8 -> 0.49104744 | C11: =C10/C8 -> 0.5516532 | D11: =D10/D8 -> 0.59321332
A13: シャチョーAの基準線：標準＝年商約（B列計算）／投資判断は標準で評価、保守で耐性確認。
